zope/app/form/__init__.py
zope/app/form/ftesting.zcml
zope/app/form/interfaces.py
zope/app/form/testing.py
zope/app/form/utility.py
zope/app/form/browser/__init__.py
zope/app/form/browser/add.pt
zope/app/form/browser/add.py
zope/app/form/browser/boolwidgets.py
zope/app/form/browser/configure.zcml
zope/app/form/browser/display.pt
zope/app/form/browser/edit.pt
zope/app/form/browser/editview.py
zope/app/form/browser/exception.py
zope/app/form/browser/form.rst
zope/app/form/browser/formview.py
zope/app/form/browser/i18n.py
zope/app/form/browser/i18n.rst
zope/app/form/browser/interfaces.py
zope/app/form/browser/itemswidgets.py
zope/app/form/browser/macros.py
zope/app/form/browser/meta.zcml
zope/app/form/browser/metaconfigure.py
zope/app/form/browser/metadirectives.py
zope/app/form/browser/objectwidget.py
zope/app/form/browser/schemadisplay.py
zope/app/form/browser/sequencewidget.py
zope/app/form/browser/source.py
zope/app/form/browser/subedit.pt
zope/app/form/browser/submit.py
zope/app/form/browser/textwidgets.py
zope/app/form/browser/widget.py
zope/app/form/browser/widgets.rst
zope/app/form/browser/tests/__init__.py
zope/app/form/browser/tests/i18n.zcml
zope/app/form/browser/tests/support.py
zope/app/form/browser/tests/test_add.py
zope/app/form/browser/tests/test_browserwidget.py
zope/app/form/browser/tests/test_directives.py
zope/app/form/browser/tests/test_editview.py
zope/app/form/browser/tests/test_form.py
zope/app/form/browser/tests/test_functional_editview.py
zope/app/form/browser/tests/test_functional_i18n.py
zope/app/form/browser/tests/test_widgetdirective.py
zope/app/form/browser/tests/testconfigure.zcml
zope/app/form/browser/tests/testeditform.pt
zope/app/form/browser/tests/testlabeltranslation.po
zope/app/form/browser/tests/widgetDirectives.zcml
zope/app/form/browser/tests/locales/formtest.pot
zope/app/form/browser/tests/locales/de/LC_MESSAGES/formtest.po
zope/app/form/tests/__init__.py
zope/app/form/tests/test_bwc_imports.py
zope_app_form-7.0.dist-info/licenses/LICENSE.txt
zope_app_form-7.0.dist-info/METADATA
zope_app_form-7.0.dist-info/WHEEL
zope_app_form-7.0.dist-info/top_level.txt
zope_app_form-7.0.dist-info/RECORD
