Metadata-Version: 2.4
Name: zope.app.form
Version: 7.0
Summary: The Original Zope 3 Form Framework
Home-page: https://github.com/zopefoundation/zope.app.form
Author: Zope Foundation and Contributors
Author-email: zope-dev@zope.dev
License: ZPL-2.1
Keywords: zope3 form widget zcml
Classifier: Development Status :: 5 - Production/Stable
Classifier: Environment :: Web Environment
Classifier: Intended Audience :: Developers
Classifier: License :: OSI Approved :: Zope Public License
Classifier: Programming Language :: Python
Classifier: Programming Language :: Python :: 3
Classifier: Programming Language :: Python :: 3.9
Classifier: Programming Language :: Python :: 3.10
Classifier: Programming Language :: Python :: 3.11
Classifier: Programming Language :: Python :: 3.12
Classifier: Programming Language :: Python :: 3.13
Classifier: Programming Language :: Python :: Implementation :: CPython
Classifier: Programming Language :: Python :: Implementation :: PyPy
Classifier: Natural Language :: English
Classifier: Operating System :: OS Independent
Classifier: Topic :: Internet :: WWW/HTTP
Classifier: Framework :: Zope :: 3
Requires-Python: >=3.9
License-File: LICENSE.txt
Requires-Dist: setuptools
Requires-Dist: transaction
Requires-Dist: zope.formlib>=4.3
Requires-Dist: zope.browser>=2.1
Requires-Dist: zope.browserpage>=3.10.1
Requires-Dist: zope.browsermenu
Requires-Dist: zope.component
Requires-Dist: zope.configuration>=4.4.0
Requires-Dist: zope.datetime
Requires-Dist: zope.exceptions
Requires-Dist: zope.i18n
Requires-Dist: zope.interface
Requires-Dist: zope.proxy
Requires-Dist: zope.publisher>=4.3.1
Requires-Dist: zope.schema>=4.4.2
Requires-Dist: zope.security
Provides-Extra: test
Requires-Dist: zc.sourcefactory; extra == "test"
Requires-Dist: zope.container; extra == "test"
Requires-Dist: zope.principalregistry; extra == "test"
Requires-Dist: zope.site; extra == "test"
Requires-Dist: zope.traversing; extra == "test"
Requires-Dist: zope.app.appsetup; extra == "test"
Requires-Dist: zope.testing; extra == "test"
Requires-Dist: zope.testrunner>=6.4; extra == "test"
Requires-Dist: zope.app.wsgi>=5.3; extra == "test"
Requires-Dist: webtest; extra == "test"
Dynamic: author
Dynamic: author-email
Dynamic: classifier
Dynamic: description
Dynamic: home-page
Dynamic: keywords
Dynamic: license
Dynamic: license-file
Dynamic: provides-extra
Dynamic: requires-dist
Dynamic: requires-python
Dynamic: summary
